{"time": 1534769795, "data": [{"name": "US30(CFD)", "value": "25709.7"}, {"name": "Bitcoin CFD(CFD)", "value": "6407.00"}, {"name": "Shanghai SE", "value": "2698.47"}, {"name": "FTSE 100(CFD)", "value": "7585.7"}, {"name": "DAX 30(CFD)", "value": "12347.01"}, {"name": "Nikkei 225(CFD)", "value": "22192.5"}, {"name": "Nifty 50", "value": "11551.75"}, {"name": "ASX 200(CFD)", "value": "6354.16"}, {"name": "FRA40(CFD)", "value": "5376.69"}, {"name": "ISE National 100", "value": "90186.00"}, {"name": "Swiss MI 20", "value": "9063.57"}, {"name": "Amsterdam EX", "value": "556.61"}, {"name": "OMXS30, Stockholm", "value": "1630.97"}, {"name": "OMXC25, Copenhagen", "value": "1150.63"}, {"name": "OMXC20, Copenhagen", "value": "1008.33"}, {"name": "OMXO20, Oslo", "value": "622.79"}, {"name": "OMXH25, Helsinki", "value": "4243.76"}, {"name": "Belgium 20", "value": "3792.74"}, {"name": "Portugal SI 20", "value": "5503.70"}, {"name": "UKOil", "value": "71.89"}, {"name": "WTI Crude", "value": "65.74"}, {"name": "US Dollar Index", "value": "96.25"}, {"name": "Gold, spot", "value": "1185.65"}, {"name": "Silver, spot", "value": "14.7"}, {"name": "Platinum, spot", "value": "792.57"}, {"name": "Palladium, spot", "value": "918.44"}]}