{"time": 1534427547, "data": [{"name": "US30(CFD)", "value": "25484.7"}, {"name": "Bitcoin CFD(CFD)", "value": "6296.8"}, {"name": "Shanghai SE", "value": "2705.19"}, {"name": "FTSE 100(CFD)", "value": "7544.8"}, {"name": "DAX 30(CFD)", "value": "12193.05"}, {"name": "Nikkei 225(CFD)", "value": "22187.5"}, {"name": "Nifty 50", "value": "11385.05"}, {"name": "ASX 200(CFD)", "value": "6326.72"}, {"name": "FRA40(CFD)", "value": "5335.17"}, {"name": "ISE National 100", "value": "88465.00"}, {"name": "Swiss MI 20", "value": "8980.03"}, {"name": "Amsterdam EX", "value": "556.23"}, {"name": "OMXS30, Stockholm", "value": "1608.85"}, {"name": "OMXC25, Copenhagen", "value": "1134.87"}, {"name": "OMXC20, Copenhagen", "value": "997.04"}, {"name": "OMXO20, Oslo", "value": "612.18"}, {"name": "OMXH25, Helsinki", "value": "4177.53"}, {"name": "Belgium 20", "value": "3770.22"}, {"name": "Portugal SI 20", "value": "5481.58"}, {"name": "UKOil", "value": "71.11"}, {"name": "WTI Crude", "value": "65.01"}, {"name": "US Dollar Index", "value": "96.49"}, {"name": "Gold, spot", "value": "1179.93"}, {"name": "Silver, spot", "value": "14.73"}, {"name": "Platinum, spot", "value": "792.58"}, {"name": "Palladium, spot", "value": "892.12"}]}