{"time": 1534767195, "data": [{"name": "US30(CFD)", "value": "25725.4"}, {"name": "Bitcoin CFD(CFD)", "value": "6423.8"}, {"name": "Shanghai SE", "value": "2698.47"}, {"name": "FTSE 100(CFD)", "value": "7584.9"}, {"name": "DAX 30(CFD)", "value": "12335.45"}, {"name": "Nikkei 225(CFD)", "value": "22217.5"}, {"name": "Nifty 50", "value": "11551.75"}, {"name": "ASX 200(CFD)", "value": "6357.06"}, {"name": "FRA40(CFD)", "value": "5381.09"}, {"name": "ISE National 100", "value": "90186.00"}, {"name": "Swiss MI 20", "value": "9051.72"}, {"name": "Amsterdam EX", "value": "556.21"}, {"name": "OMXS30, Stockholm", "value": "1629.38"}, {"name": "OMXC25, Copenhagen", "value": "1146.87"}, {"name": "OMXC20, Copenhagen", "value": "1004.61"}, {"name": "OMXO20, Oslo", "value": "622.31"}, {"name": "OMXH25, Helsinki", "value": "4236.53"}, {"name": "Belgium 20", "value": "3788.92"}, {"name": "Portugal SI 20", "value": "5499.43"}, {"name": "UKOil", "value": "72.19"}, {"name": "WTI Crude", "value": "65.90"}, {"name": "US Dollar Index", "value": "96.22"}, {"name": "Gold, spot", "value": "1186.36"}, {"name": "Silver, spot", "value": "14.71"}, {"name": "Platinum, spot", "value": "792.05"}, {"name": "Palladium, spot", "value": "916.82"}]}