{"time": 1534512025, "data": [{"name": "US30(CFD)", "value": "25518.9"}, {"name": "Bitcoin CFD(CFD)", "value": "6454.1"}, {"name": "Shanghai SE", "value": "2668.97"}, {"name": "FTSE 100(CFD)", "value": "7516.2"}, {"name": "DAX 30(CFD)", "value": "12144.55"}, {"name": "Nikkei 225(CFD)", "value": "22117.5"}, {"name": "Nifty 50", "value": "11470.75"}, {"name": "ASX 200(CFD)", "value": "6341.77"}, {"name": "FRA40(CFD)", "value": "5316.61"}, {"name": "ISE National 100", "value": "86123.00"}, {"name": "Swiss MI 20", "value": "8972.40"}, {"name": "Amsterdam EX", "value": "551.08"}, {"name": "OMXS30, Stockholm", "value": "1615.20"}, {"name": "OMXC25, Copenhagen", "value": "1138.81"}, {"name": "OMXC20, Copenhagen", "value": "998.15"}, {"name": "OMXO20, Oslo", "value": "614.21"}, {"name": "OMXH25, Helsinki", "value": "4182.08"}, {"name": "Belgium 20", "value": "3756.27"}, {"name": "Portugal SI 20", "value": "5443.51"}, {"name": "UKOil", "value": "72.34"}, {"name": "WTI Crude", "value": "66.17"}, {"name": "US Dollar Index", "value": "96.32"}, {"name": "Gold, spot", "value": "1179.00"}, {"name": "Silver, spot", "value": "14.67"}, {"name": "Platinum, spot", "value": "778.47"}, {"name": "Palladium, spot", "value": "894.32"}]}