{"time": 1534427007, "data": [{"name": "US30(CFD)", "value": "25457.55"}, {"name": "Bitcoin CFD(CFD)", "value": "6300.6"}, {"name": "Shanghai SE", "value": "2705.19"}, {"name": "FTSE 100(CFD)", "value": "7549.5"}, {"name": "DAX 30(CFD)", "value": "12195.73"}, {"name": "Nikkei 225(CFD)", "value": "22177.5"}, {"name": "Nifty 50", "value": "11385.05"}, {"name": "ASX 200(CFD)", "value": "6321.72"}, {"name": "FRA40(CFD)", "value": "5334.67"}, {"name": "ISE National 100", "value": "87954.00"}, {"name": "Swiss MI 20", "value": "8977.20"}, {"name": "Amsterdam EX", "value": "556.00"}, {"name": "OMXS30, Stockholm", "value": "1609.26"}, {"name": "OMXC25, Copenhagen", "value": "1134.69"}, {"name": "OMXC20, Copenhagen", "value": "996.91"}, {"name": "OMXO20, Oslo", "value": "612.02"}, {"name": "OMXH25, Helsinki", "value": "4180.04"}, {"name": "Belgium 20", "value": "3769.78"}, {"name": "Portugal SI 20", "value": "5483.49"}, {"name": "UKOil", "value": "70.89"}, {"name": "WTI Crude", "value": "65.00"}, {"name": "US Dollar Index", "value": "96.53"}, {"name": "Gold, spot", "value": "1178.78"}, {"name": "Silver, spot", "value": "14.68"}, {"name": "Platinum, spot", "value": "788.51"}, {"name": "Palladium, spot", "value": "887.32"}]}