{"time": 1522226539, "data": [{"name": "US30(CFD)", "value": "23809.6"}, {"name": "Bitcoin CFD(CFD)", "value": "7863.7"}, {"name": "Shanghai SE", "value": "3122.29"}, {"name": "FTSE 100(CFD)", "value": "6924.99"}, {"name": "DAX 30(CFD)", "value": "11790.97"}, {"name": "Nikkei 225(CFD)", "value": "20909.5"}, {"name": "Nifty 50", "value": "10139.15"}, {"name": "ASX 200(CFD)", "value": "5775.2"}, {"name": "FRA40(CFD)", "value": "5044.34"}, {"name": "ISE National 100", "value": "115651.00"}, {"name": "Swiss MI 20", "value": "8558.30"}, {"name": "Amsterdam EX", "value": "520.10"}, {"name": "OMXS30, Stockholm", "value": "1491.29"}, {"name": "OMXC25, Copenhagen", "value": "1104.42"}, {"name": "OMXC20, Copenhagen", "value": "967.04"}, {"name": "OMXO20, Oslo", "value": "554.39"}, {"name": "OMXH25, Helsinki", "value": "3949.85"}, {"name": "Belgium 20", "value": "3796.06"}, {"name": "Portugal SI 20", "value": "5322.03"}, {"name": "UKOil", "value": "69.61"}, {"name": "WTI Crude", "value": "64.62"}, {"name": "US Dollar Index", "value": "89.42"}, {"name": "Gold, spot", "value": "1342.33"}, {"name": "Silver, spot", "value": "16.49"}, {"name": "Platinum, spot", "value": "942.72"}, {"name": "Palladium, spot", "value": "975.39"}]}