{"time": 1535016437, "data": [{"name": "US30(CFD)", "value": "25721.00"}, {"name": "Bitcoin CFD(CFD)", "value": "6362.6"}, {"name": "Shanghai SE", "value": "2724.62"}, {"name": "FTSE 100(CFD)", "value": "7578.5"}, {"name": "DAX 30(CFD)", "value": "12392.00"}, {"name": "Nikkei 225(CFD)", "value": "22442.5"}, {"name": "Nifty 50", "value": "11588.15"}, {"name": "ASX 200(CFD)", "value": "6256.22"}, {"name": "FRA40(CFD)", "value": "5431.95"}, {"name": "ISE National 100", "value": "90186.00"}, {"name": "Swiss MI 20", "value": "9069.31"}, {"name": "Amsterdam EX", "value": "561.48"}, {"name": "OMXS30, Stockholm", "value": "1648.43"}, {"name": "OMXC25, Copenhagen", "value": "1164.85"}, {"name": "OMXC20, Copenhagen", "value": "1021.74"}, {"name": "OMXO20, Oslo", "value": "625.34"}, {"name": "OMXH25, Helsinki", "value": "4299.02"}, {"name": "Belgium 20", "value": "3808.79"}, {"name": "Portugal SI 20", "value": "5499.20"}, {"name": "UKOil", "value": "74.47"}, {"name": "WTI Crude", "value": "67.76"}, {"name": "US Dollar Index", "value": "95.45"}, {"name": "Gold, spot", "value": "1187.06"}, {"name": "Silver, spot", "value": "14.55"}, {"name": "Platinum, spot", "value": "777.49"}, {"name": "Palladium, spot", "value": "912.33"}]}