{"time": 1534951696, "data": [{"name": "US30(CFD)", "value": "25813.4"}, {"name": "Bitcoin CFD(CFD)", "value": "6618.3"}, {"name": "Shanghai SE", "value": "2714.61"}, {"name": "FTSE 100(CFD)", "value": "7578.9"}, {"name": "DAX 30(CFD)", "value": "12385.13"}, {"name": "Nikkei 225(CFD)", "value": "22452.5"}, {"name": "Nifty 50", "value": "11570.90"}, {"name": "ASX 200(CFD)", "value": "6287.34"}, {"name": "FRA40(CFD)", "value": "5422.57"}, {"name": "ISE National 100", "value": "90186.00"}, {"name": "Swiss MI 20", "value": "9043.78"}, {"name": "Amsterdam EX", "value": "559.21"}, {"name": "OMXS30, Stockholm", "value": "1642.46"}, {"name": "OMXC25, Copenhagen", "value": "1159.12"}, {"name": "OMXC20, Copenhagen", "value": "1016.40"}, {"name": "OMXO20, Oslo", "value": "624.14"}, {"name": "OMXH25, Helsinki", "value": "4285.47"}, {"name": "Belgium 20", "value": "3799.38"}, {"name": "Portugal SI 20", "value": "5518.93"}, {"name": "UKOil", "value": "74.31"}, {"name": "WTI Crude", "value": "67.48"}, {"name": "US Dollar Index", "value": "95.08"}, {"name": "Gold, spot", "value": "1195.25"}, {"name": "Silver, spot", "value": "14.74"}, {"name": "Platinum, spot", "value": "793.62"}, {"name": "Palladium, spot", "value": "921.75"}]}