{"time": 1534494562, "data": [{"name": "US30(CFD)", "value": "25618.9"}, {"name": "Bitcoin CFD(CFD)", "value": "6418.7"}, {"name": "Shanghai SE", "value": "2668.97"}, {"name": "FTSE 100(CFD)", "value": "7567.4"}, {"name": "DAX 30(CFD)", "value": "12233.45"}, {"name": "Nikkei 225(CFD)", "value": "22257.5"}, {"name": "Nifty 50", "value": "11462.65"}, {"name": "ASX 200(CFD)", "value": "6345.57"}, {"name": "FRA40(CFD)", "value": "5361.11"}, {"name": "ISE National 100", "value": "86171.00"}, {"name": "Swiss MI 20", "value": "9021.49"}, {"name": "Amsterdam EX", "value": "555.80"}, {"name": "OMXS30, Stockholm", "value": "1615.10"}, {"name": "OMXC25, Copenhagen", "value": "1143.60"}, {"name": "OMXC20, Copenhagen", "value": "1002.61"}, {"name": "OMXO20, Oslo", "value": "616.73"}, {"name": "OMXH25, Helsinki", "value": "4210.27"}, {"name": "Belgium 20", "value": "3784.96"}, {"name": "Portugal SI 20", "value": "5488.85"}, {"name": "UKOil", "value": "71.72"}, {"name": "WTI Crude", "value": "65.66"}, {"name": "US Dollar Index", "value": "96.33"}, {"name": "Gold, spot", "value": "1178.21"}, {"name": "Silver, spot", "value": "14.72"}, {"name": "Platinum, spot", "value": "782.83"}, {"name": "Palladium, spot", "value": "902.72"}]}