{"time": 1522243457, "data": [{"name": "US30(CFD)", "value": "23943.4"}, {"name": "Bitcoin CFD(CFD)", "value": "7993.9"}, {"name": "Shanghai SE", "value": "3122.29"}, {"name": "FTSE 100(CFD)", "value": "7005.99"}, {"name": "DAX 30(CFD)", "value": "11910.77"}, {"name": "Nikkei 225(CFD)", "value": "21069.5"}, {"name": "Nifty 50", "value": "10113.70"}, {"name": "ASX 200(CFD)", "value": "5797.2"}, {"name": "FRA40(CFD)", "value": "5104.43"}, {"name": "ISE National 100", "value": "114467.00"}, {"name": "Swiss MI 20", "value": "8644.10"}, {"name": "Amsterdam EX", "value": "524.27"}, {"name": "OMXS30, Stockholm", "value": "1501.80"}, {"name": "OMXC25, Copenhagen", "value": "1116.42"}, {"name": "OMXC20, Copenhagen", "value": "979.35"}, {"name": "OMXO20, Oslo", "value": "559.17"}, {"name": "OMXH25, Helsinki", "value": "3974.18"}, {"name": "Belgium 20", "value": "3833.25"}, {"name": "Portugal SI 20", "value": "5324.32"}, {"name": "UKOil", "value": "69.72"}, {"name": "WTI Crude", "value": "64.71"}, {"name": "US Dollar Index", "value": "89.69"}, {"name": "Gold, spot", "value": "1333.95"}, {"name": "Silver, spot", "value": "16.37"}, {"name": "Platinum, spot", "value": "939.41"}, {"name": "Palladium, spot", "value": "974.71"}]}