{"time": 1534434328, "data": [{"name": "US30(CFD)", "value": "25522.35"}, {"name": "Bitcoin CFD(CFD)", "value": "6374.1"}, {"name": "Shanghai SE", "value": "2705.19"}, {"name": "FTSE 100(CFD)", "value": "7561.9"}, {"name": "DAX 30(CFD)", "value": "12228.65"}, {"name": "Nikkei 225(CFD)", "value": "22262.5"}, {"name": "Nifty 50", "value": "11385.05"}, {"name": "ASX 200(CFD)", "value": "6323.72"}, {"name": "FRA40(CFD)", "value": "5348.17"}, {"name": "ISE National 100", "value": "87143.00"}, {"name": "Swiss MI 20", "value": "8999.09"}, {"name": "Amsterdam EX", "value": "557.01"}, {"name": "OMXS30, Stockholm", "value": "1611.33"}, {"name": "OMXC25, Copenhagen", "value": "1140.35"}, {"name": "OMXC20, Copenhagen", "value": "1002.22"}, {"name": "OMXO20, Oslo", "value": "612.43"}, {"name": "OMXH25, Helsinki", "value": "4186.71"}, {"name": "Belgium 20", "value": "3777.16"}, {"name": "Portugal SI 20", "value": "5485.75"}, {"name": "UKOil", "value": "71.09"}, {"name": "WTI Crude", "value": "65.45"}, {"name": "US Dollar Index", "value": "96.47"}, {"name": "Gold, spot", "value": "1179.41"}, {"name": "Silver, spot", "value": "14.78"}, {"name": "Platinum, spot", "value": "791.44"}, {"name": "Palladium, spot", "value": "902.32"}]}